{
  "id": "projects_list",
  "type": "SharedSlice",
  "name": "ProjectsList",
  "description": "ProjectsList",
  "variations": [
    {
      "id": "default",
      "name": "Default",
      "docURL": "...",
      "version": "sktwi1xtmkfgx8626",
      "description": "ProjectsList",
      "primary": {
        "introduction": {
          "type": "StructuredText",
          "config": {
            "label": "Introduction",
            "placeholder": "A nice description of your feature",
            "allowTargetBlank": true,
            "single": "paragraph"
          }
        }
      },
      "items": {
        "title": {
          "type": "Text",
          "config": {
            "label": "Titre",
            "placeholder": ""
          }
        },
        "main_image": {
          "type": "Image",
          "config": {
            "label": "Image principale",
            "constraint": {},
            "thumbnails": []
          }
        }
      },
      "imageUrl": "https://images.prismic.io/slice-machine/621a5ec4-0387-4bc5-9860-2dd46cbc07cd_default_ss.png?auto=compress,format"
    }
  ]
}